{
  "x58hPGCkMV0sbQMo": {
    "id": "x58hPGCkMV0sbQMo",
    "name": "Night",
    "sounds": [
      {
        "id": "zxUdOkqDRUvWkHDf",
        "_id": "zxUdOkqDRUvWkHDf",
        "status": "off",
        "group": "Rain",
        "name": "rain1.mp3",
        "description": "This sound is managed by the Soundscape Adventure",
        "path": "modules/soundscape-adventure/sample-root-soundscapes/Global/Loop/Rain/rain1.mp3",
        "repeat": true,
        "volume": 0,
        "type": 4,
        "intensity": 0
      },
      {
        "id": "CbhJReYO3SF8BL5t",
        "_id": "CbhJReYO3SF8BL5t",
        "status": "off",
        "group": "Rain",
        "name": "rain2.mp3",
        "description": "This sound is managed by the Soundscape Adventure",
        "path": "modules/soundscape-adventure/sample-root-soundscapes/Global/Loop/Rain/rain2.mp3",
        "repeat": true,
        "volume": 0,
        "type": 4,
        "intensity": 0
      },
      {
        "id": "OAXwgoPrYpfVy1ve",
        "_id": "OAXwgoPrYpfVy1ve",
        "status": "off",
        "group": "Rain",
        "name": "rain3.mp3",
        "description": "This sound is managed by the Soundscape Adventure",
        "path": "modules/soundscape-adventure/sample-root-soundscapes/Global/Loop/Rain/rain3.mp3",
        "repeat": true,
        "volume": 0,
        "type": 4,
        "intensity": 0
      },
      {
        "id": "CAT2LHki27UydMPB",
        "_id": "CAT2LHki27UydMPB",
        "status": "off",
        "group": "Rain",
        "name": "rain4.mp3",
        "description": "This sound is managed by the Soundscape Adventure",
        "path": "modules/soundscape-adventure/sample-root-soundscapes/Global/Loop/Rain/rain4.mp3",
        "repeat": true,
        "volume": 0,
        "type": 4,
        "intensity": 0
      },
      {
        "id": "R0EXUnFViV0s5ipG",
        "_id": "R0EXUnFViV0s5ipG",
        "status": "off",
        "group": "Rain",
        "name": "rain5.mp3",
        "description": "This sound is managed by the Soundscape Adventure",
        "path": "modules/soundscape-adventure/sample-root-soundscapes/Global/Loop/Rain/rain5.mp3",
        "repeat": true,
        "volume": 0,
        "type": 4,
        "intensity": 0
      },
      {
        "id": "UWoYWu472rjx9ZSU",
        "_id": "UWoYWu472rjx9ZSU",
        "status": "on",
        "group": "",
        "name": "Piano Solo",
        "description": "This sound is managed by the Soundscape Adventure",
        "path": "modules/soundscape-adventure/sample-root-soundscapes/Forest/Ambience/afternoon-ambient-piano-solo-24367.mp3",
        "repeat": true,
        "volume": "0.5",
        "type": 0,
        "intensity": 0
      },
      {
        "id": "OTaIQDMnFOOkqlV4",
        "_id": "OTaIQDMnFOOkqlV4",
        "status": "on",
        "group": "",
        "name": "Bondfire",
        "description": "This sound is managed by the Soundscape Adventure",
        "path": "modules/soundscape-adventure/sample-root-soundscapes/Forest/Loop/fire-burning-loop.mp3",
        "repeat": true,
        "volume": "0.1",
        "type": 1,
        "intensity": 0
      },
      {
        "id": "32meem1H71yLnHzr",
        "_id": "32meem1H71yLnHzr",
        "status": "on",
        "group": "",
        "name": "Night Summer",
        "description": "This sound is managed by the Soundscape Adventure",
        "path": "modules/soundscape-adventure/sample-root-soundscapes/Forest/Loop/nightsummer-87503.mp3",
        "repeat": true,
        "volume": "0.3",
        "type": 1,
        "intensity": 0
      },
      {
        "id": "LfThliJloE1gUtRf",
        "_id": "LfThliJloE1gUtRf",
        "status": "off",
        "group": "",
        "name": "Thunder",
        "description": "This sound is managed by the Soundscape Adventure",
        "path": "modules/soundscape-adventure/sample-root-soundscapes/Forest/Random/loud-thunder-192165.mp3",
        "repeat": false,
        "volume": 0,
        "type": 2,
        "intensity": 0
      },
      {
        "id": "K44pVC70sIxeDts6",
        "_id": "K44pVC70sIxeDts6",
        "status": "on",
        "group": "NighAnimals",
        "name": "Cricket.mp3",
        "description": "This sound is managed by the Soundscape Adventure",
        "path": "modules/soundscape-adventure/sample-root-soundscapes/Forest/Random/NighAnimals/Cricket.mp3",
        "repeat": false,
        "volume": "0.4",
        "type": 5,
        "intensity": 0
      },
      {
        "id": "mOUfIknOUuKO5R65",
        "_id": "mOUfIknOUuKO5R65",
        "status": "on",
        "group": "NighAnimals",
        "name": "Owl.mp3",
        "description": "This sound is managed by the Soundscape Adventure",
        "path": "modules/soundscape-adventure/sample-root-soundscapes/Forest/Random/NighAnimals/Owl.mp3",
        "repeat": false,
        "volume": "0.4",
        "type": 5,
        "intensity": 0
      }
    ]
  },
  "gAFXsplbxI0vaZ3T": {
    "id": "gAFXsplbxI0vaZ3T",
    "name": "Night Raining",
    "sounds": [
      {
        "id": "zxUdOkqDRUvWkHDf",
        "_id": "zxUdOkqDRUvWkHDf",
        "status": "on",
        "group": "Rain",
        "name": "rain1.mp3",
        "description": "This sound is managed by the Soundscape Adventure",
        "path": "modules/soundscape-adventure/sample-root-soundscapes/Global/Loop/Rain/rain1.mp3",
        "repeat": true,
        "volume": "0.55",
        "type": 4,
        "intensity": 0
      },
      {
        "id": "CbhJReYO3SF8BL5t",
        "_id": "CbhJReYO3SF8BL5t",
        "status": "on",
        "group": "Rain",
        "name": "rain2.mp3",
        "description": "This sound is managed by the Soundscape Adventure",
        "path": "modules/soundscape-adventure/sample-root-soundscapes/Global/Loop/Rain/rain2.mp3",
        "repeat": true,
        "volume": "0.55",
        "type": 4,
        "intensity": 0
      },
      {
        "id": "OAXwgoPrYpfVy1ve",
        "_id": "OAXwgoPrYpfVy1ve",
        "status": "on",
        "group": "Rain",
        "name": "rain3.mp3",
        "description": "This sound is managed by the Soundscape Adventure",
        "path": "modules/soundscape-adventure/sample-root-soundscapes/Global/Loop/Rain/rain3.mp3",
        "repeat": true,
        "volume": "0.55",
        "type": 4,
        "intensity": 0
      },
      {
        "id": "CAT2LHki27UydMPB",
        "_id": "CAT2LHki27UydMPB",
        "status": "on",
        "group": "Rain",
        "name": "rain4.mp3",
        "description": "This sound is managed by the Soundscape Adventure",
        "path": "modules/soundscape-adventure/sample-root-soundscapes/Global/Loop/Rain/rain4.mp3",
        "repeat": true,
        "volume": "0.55",
        "type": 4,
        "intensity": 0
      },
      {
        "id": "R0EXUnFViV0s5ipG",
        "_id": "R0EXUnFViV0s5ipG",
        "status": "on",
        "group": "Rain",
        "name": "rain5.mp3",
        "description": "This sound is managed by the Soundscape Adventure",
        "path": "modules/soundscape-adventure/sample-root-soundscapes/Global/Loop/Rain/rain5.mp3",
        "repeat": true,
        "volume": "0.55",
        "type": 4,
        "intensity": 0
      },
      {
        "id": "UWoYWu472rjx9ZSU",
        "_id": "UWoYWu472rjx9ZSU",
        "status": "on",
        "group": "",
        "name": "Piano Solo",
        "description": "This sound is managed by the Soundscape Adventure",
        "path": "modules/soundscape-adventure/sample-root-soundscapes/Forest/Ambience/afternoon-ambient-piano-solo-24367.mp3",
        "repeat": true,
        "volume": "0.2",
        "type": 0,
        "intensity": 0
      },
      {
        "id": "OTaIQDMnFOOkqlV4",
        "_id": "OTaIQDMnFOOkqlV4",
        "status": "on",
        "group": "",
        "name": "Bondfire",
        "description": "This sound is managed by the Soundscape Adventure",
        "path": "modules/soundscape-adventure/sample-root-soundscapes/Forest/Loop/fire-burning-loop.mp3",
        "repeat": true,
        "volume": "0.05",
        "type": 1,
        "intensity": 0
      },
      {
        "id": "32meem1H71yLnHzr",
        "_id": "32meem1H71yLnHzr",
        "status": "on",
        "group": "",
        "name": "Night Summer",
        "description": "This sound is managed by the Soundscape Adventure",
        "path": "modules/soundscape-adventure/sample-root-soundscapes/Forest/Loop/nightsummer-87503.mp3",
        "repeat": true,
        "volume": "0.15",
        "type": 1,
        "intensity": 0
      },
      {
        "id": "LfThliJloE1gUtRf",
        "_id": "LfThliJloE1gUtRf",
        "status": "on",
        "group": "",
        "name": "Thunder",
        "description": "This sound is managed by the Soundscape Adventure",
        "path": "modules/soundscape-adventure/sample-root-soundscapes/Forest/Random/loud-thunder-192165.mp3",
        "repeat": false,
        "volume": "0.65",
        "type": 2,
        "intensity": 0
      },
      {
        "id": "K44pVC70sIxeDts6",
        "_id": "K44pVC70sIxeDts6",
        "status": "off",
        "group": "NighAnimals",
        "name": "Cricket.mp3",
        "description": "This sound is managed by the Soundscape Adventure",
        "path": "modules/soundscape-adventure/sample-root-soundscapes/Forest/Random/NighAnimals/Cricket.mp3",
        "repeat": false,
        "volume": 0,
        "type": 5,
        "intensity": 0
      },
      {
        "id": "mOUfIknOUuKO5R65",
        "_id": "mOUfIknOUuKO5R65",
        "status": "off",
        "group": "NighAnimals",
        "name": "Owl.mp3",
        "description": "This sound is managed by the Soundscape Adventure",
        "path": "modules/soundscape-adventure/sample-root-soundscapes/Forest/Random/NighAnimals/Owl.mp3",
        "repeat": false,
        "volume": 0,
        "type": 5,
        "intensity": 0
      }
    ]
  }
}